cicd_example/Example.py
cicd_example/main.py
fuyao-0.0.1.dist-info/WHEEL
fuyao-0.0.1.dist-info/METADATA
fuyao-0.0.1.dist-info/RECORD
