Metadata-Version: 2.1
Name: fuyao
Version: 0.0.1
Summary:  
Author: Erik Li
Author-email: erikl@xiaopeng.com
Requires-Python: >=3.5,<4.0
Classifier: Programming Language :: Python :: 3
Classifier: Programming Language :: Python :: 3.10
Classifier: Programming Language :: Python :: 3.5
Classifier: Programming Language :: Python :: 3.6
Classifier: Programming Language :: Python :: 3.7
Classifier: Programming Language :: Python :: 3.8
Classifier: Programming Language :: Python :: 3.9
Requires-Dist: pytest (==6.1.2)
Requires-Dist: requests[security] (==2.25.1)
